{"mediaFiles":[{"id":87,"filename":"protoksit.png","originalName":"protoksit.png","mimeType":"image/png","size":868157,"url":"/gallery/protoksit.png","originalPath":"/gallery/protoksit.png","uploadedBy":1,"deletedAt":null,"createdAt":"2025-12-20T16:19:33.000Z","updatedAt":"2025-12-20T16:44:15.000Z"},{"id":86,"filename":"propan.png","originalName":"propan.png","mimeType":"image/png","size":386893,"url":"/gallery/propan.png","originalPath":"/gallery/propan.png","uploadedBy":1,"deletedAt":null,"createdAt":"2025-12-20T16:19:33.000Z","updatedAt":"2025-12-20T16:44:15.000Z"},{"id":85,"filename":"ozel-gaz.png","originalName":"ozel-gaz.png","mimeType":"image/png","size":886242,"url":"/gallery/ozel-gaz.png","originalPath":"/gallery/ozel-gaz.png","uploadedBy":1,"deletedAt":null,"createdAt":"2025-12-20T16:19:32.000Z","updatedAt":"2025-12-20T16:44:15.000Z"},{"id":84,"filename":"medikal-oksijen.png","originalName":"medikal-oksijen.png","mimeType":"image/png","size":388559,"url":"/gallery/medikal-oksijen.png","originalPath":"/gallery/medikal-oksijen.png","uploadedBy":1,"deletedAt":null,"createdAt":"2025-12-20T16:19:32.000Z","updatedAt":"2025-12-20T16:44:15.000Z"},{"id":83,"filename":"kuru-hava.png","originalName":"kuru-hava.png","mimeType":"image/png","size":570514,"url":"/gallery/kuru-hava.png","originalPath":"/gallery/kuru-hava.png","uploadedBy":1,"deletedAt":null,"createdAt":"2025-12-20T16:19:31.000Z","updatedAt":"2025-12-20T16:44:15.000Z"},{"id":82,"filename":"kriyojenik-tup.png","originalName":"kriyojenik-tup.png","mimeType":"image/png","size":154333,"url":"/gallery/kriyojenik-tup.png","originalPath":"/gallery/kriyojenik-tup.png","uploadedBy":1,"deletedAt":null,"createdAt":"2025-12-20T16:19:31.000Z","updatedAt":"2025-12-20T16:44:15.000Z"},{"id":81,"filename":"kaynak-mix-3.png","originalName":"kaynak-mix-3.png","mimeType":"image/png","size":879891,"url":"/gallery/kaynak-mix-3.png","originalPath":"/gallery/kaynak-mix-3.png","uploadedBy":1,"deletedAt":null,"createdAt":"2025-12-20T16:19:30.000Z","updatedAt":"2025-12-20T16:44:15.000Z"},{"id":80,"filename":"kaynak-mix-2.png","originalName":"kaynak-mix-2.png","mimeType":"image/png","size":878220,"url":"/gallery/kaynak-mix-2.png","originalPath":"/gallery/kaynak-mix-2.png","uploadedBy":1,"deletedAt":null,"createdAt":"2025-12-20T16:19:30.000Z","updatedAt":"2025-12-20T16:44:15.000Z"},{"id":79,"filename":"kaynak-mix-1.png","originalName":"kaynak-mix-1.png","mimeType":"image/png","size":883708,"url":"/gallery/kaynak-mix-1.png","originalPath":"/gallery/kaynak-mix-1.png","uploadedBy":1,"deletedAt":null,"createdAt":"2025-12-20T16:19:29.000Z","updatedAt":"2025-12-20T16:44:15.000Z"},{"id":78,"filename":"kaynak-gazi.png","originalName":"kaynak-gazi.png","mimeType":"image/png","size":854645,"url":"/gallery/kaynak-gazi.png","originalPath":"/gallery/kaynak-gazi.png","uploadedBy":1,"deletedAt":null,"createdAt":"2025-12-20T16:19:29.000Z","updatedAt":"2025-12-20T16:44:15.000Z"},{"id":77,"filename":"karbondioksit.png","originalName":"karbondioksit.png","mimeType":"image/png","size":386893,"url":"/gallery/karbondioksit.png","originalPath":"/gallery/karbondioksit.png","uploadedBy":1,"deletedAt":null,"createdAt":"2025-12-20T16:19:28.000Z","updatedAt":"2025-12-20T16:44:15.000Z"},{"id":76,"filename":"hidrojen.png","originalName":"hidrojen.png","mimeType":"image/png","size":875744,"url":"/gallery/hidrojen.png","originalPath":"/gallery/hidrojen.png","uploadedBy":1,"deletedAt":null,"createdAt":"2025-12-20T16:19:28.000Z","updatedAt":"2025-12-20T16:44:15.000Z"},{"id":75,"filename":"helyum.png","originalName":"helyum.png","mimeType":"image/png","size":393859,"url":"/gallery/helyum.png","originalPath":"/gallery/helyum.png","uploadedBy":1,"deletedAt":null,"createdAt":"2025-12-20T16:19:27.000Z","updatedAt":"2025-12-20T16:44:15.000Z"},{"id":74,"filename":"gida-gazi-mix.png","originalName":"gida-gazi-mix.png","mimeType":"image/png","size":880425,"url":"/gallery/gida-gazi-mix.png","originalPath":"/gallery/gida-gazi-mix.png","uploadedBy":1,"deletedAt":null,"createdAt":"2025-12-20T16:19:27.000Z","updatedAt":"2025-12-20T16:44:15.000Z"},{"id":73,"filename":"endustriyel-oksijen.png","originalName":"endustriyel-oksijen.png","mimeType":"image/png","size":385598,"url":"/gallery/endustriyel-oksijen.png","originalPath":"/gallery/endustriyel-oksijen.png","uploadedBy":1,"deletedAt":null,"createdAt":"2025-12-20T16:19:26.000Z","updatedAt":"2025-12-20T16:44:15.000Z"},{"id":72,"filename":"balon-gazi.png","originalName":"balon-gazi.png","mimeType":"image/png","size":878220,"url":"/gallery/balon-gazi.png","originalPath":"/gallery/balon-gazi.png","uploadedBy":1,"deletedAt":null,"createdAt":"2025-12-20T16:19:25.000Z","updatedAt":"2025-12-20T16:44:15.000Z"},{"id":71,"filename":"azot.png","originalName":"azot.png","mimeType":"image/png","size":393859,"url":"/gallery/azot.png","originalPath":"/gallery/azot.png","uploadedBy":1,"deletedAt":null,"createdAt":"2025-12-20T16:19:25.000Z","updatedAt":"2025-12-20T16:44:15.000Z"},{"id":70,"filename":"asetilen.png","originalName":"asetilen.png","mimeType":"image/png","size":423403,"url":"/gallery/asetilen.png","originalPath":"/gallery/asetilen.png","uploadedBy":1,"deletedAt":null,"createdAt":"2025-12-20T16:19:24.000Z","updatedAt":"2025-12-20T16:44:15.000Z"},{"id":69,"filename":"argon.png","originalName":"argon.png","mimeType":"image/png","size":469860,"url":"/gallery/argon.png","originalPath":"/gallery/argon.png","uploadedBy":1,"deletedAt":null,"createdAt":"2025-12-20T16:19:24.000Z","updatedAt":"2025-12-20T16:44:15.000Z"},{"id":68,"filename":"amonyak.png","originalName":"amonyak.png","mimeType":"image/png","size":868996,"url":"/gallery/amonyak.png","originalPath":"/gallery/amonyak.png","uploadedBy":1,"deletedAt":null,"createdAt":"2025-12-20T16:19:23.000Z","updatedAt":"2025-12-20T16:44:15.000Z"},{"id":66,"filename":"hero-slide-welding.jpg","originalName":"hero-slide-welding.jpg","mimeType":"image/jpeg","size":476731,"url":"/hero/hero-slide-welding.jpg","originalPath":null,"uploadedBy":1,"deletedAt":null,"createdAt":"2025-12-20T15:46:52.000Z","updatedAt":"2025-12-20T15:46:52.000Z"},{"id":65,"filename":"hero-slide-food.jpg","originalName":"hero-slide-food.jpg","mimeType":"image/jpeg","size":330023,"url":"/hero/hero-slide-food.jpg","originalPath":null,"uploadedBy":1,"deletedAt":null,"createdAt":"2025-12-20T15:46:50.000Z","updatedAt":"2025-12-20T15:46:50.000Z"},{"id":64,"filename":"hero-slide-factory.jpg","originalName":"hero-slide-factory.jpg","mimeType":"image/jpeg","size":312633,"url":"/hero/hero-slide-factory.jpg","originalPath":null,"uploadedBy":1,"deletedAt":null,"createdAt":"2025-12-20T15:46:50.000Z","updatedAt":"2025-12-20T15:46:50.000Z"},{"id":63,"filename":"ozel-gaz-karisim-service.jpg","originalName":"ozel-gaz-karisim-service.jpg","mimeType":"image/jpeg","size":86842,"url":"/services/ozel-gaz-karisim-service.jpg","originalPath":null,"uploadedBy":1,"deletedAt":null,"createdAt":"2025-12-20T15:45:25.000Z","updatedAt":"2025-12-20T15:45:25.000Z"},{"id":62,"filename":"medikal-gazlar-service.jpg","originalName":"medikal-gazlar-service.jpg","mimeType":"image/jpeg","size":74589,"url":"/services/medikal-gazlar-service.jpg","originalPath":null,"uploadedBy":1,"deletedAt":null,"createdAt":"2025-12-20T15:45:24.000Z","updatedAt":"2025-12-20T15:45:24.000Z"},{"id":61,"filename":"kaynak-gazlari-service.jpg","originalName":"kaynak-gazlari-service.jpg","mimeType":"image/jpeg","size":173275,"url":"/services/kaynak-gazlari-service.jpg","originalPath":null,"uploadedBy":1,"deletedAt":null,"createdAt":"2025-12-20T15:45:24.000Z","updatedAt":"2025-12-20T15:45:24.000Z"},{"id":60,"filename":"gida-gazlari-service.jpg","originalName":"gida-gazlari-service.jpg","mimeType":"image/jpeg","size":67235,"url":"/services/gida-gazlari-service.jpg","originalPath":null,"uploadedBy":1,"deletedAt":null,"createdAt":"2025-12-20T15:45:23.000Z","updatedAt":"2025-12-20T15:45:23.000Z"},{"id":59,"filename":"endustriyel-gaz-service.jpg","originalName":"endustriyel-gaz-service.jpg","mimeType":"image/jpeg","size":109925,"url":"/services/endustriyel-gaz-service.jpg","originalPath":null,"uploadedBy":1,"deletedAt":null,"createdAt":"2025-12-20T15:45:23.000Z","updatedAt":"2025-12-20T15:45:23.000Z"},{"id":38,"filename":"new-year-bg.png","originalName":"new-year-bg.jpg","mimeType":"image/png","size":1142,"url":"/templates/new-year-bg.png","originalPath":null,"uploadedBy":1,"deletedAt":null,"createdAt":"2025-12-20T15:40:46.000Z","updatedAt":"2025-12-20T16:53:07.000Z"},{"id":37,"filename":"window.svg","originalName":"window.svg","mimeType":"image/svg+xml","size":385,"url":"/window.svg","originalPath":null,"uploadedBy":1,"deletedAt":null,"createdAt":"2025-12-20T13:52:13.000Z","updatedAt":"2025-12-20T13:52:13.000Z"},{"id":36,"filename":"vercel.svg","originalName":"vercel.svg","mimeType":"image/svg+xml","size":128,"url":"/vercel.svg","originalPath":null,"uploadedBy":1,"deletedAt":null,"createdAt":"2025-12-20T13:52:13.000Z","updatedAt":"2025-12-20T13:52:13.000Z"},{"id":31,"filename":"medikal-gazlar-custom.jpg","originalName":"medikal-gazlar-custom.jpg","mimeType":"image/jpeg","size":72295,"url":"/products/medikal-gazlar-custom.jpg","originalPath":"/products/medikal-gazlar-custom.jpg","uploadedBy":1,"deletedAt":null,"createdAt":"2025-12-20T13:52:10.000Z","updatedAt":"2025-12-20T16:48:04.000Z"},{"id":28,"filename":"kriyojenik-sivilar-custom.jpg","originalName":"kriyojenik-sivilar-custom.jpg","mimeType":"image/jpeg","size":104661,"url":"/products/kriyojenik-sivilar-custom.jpg","originalPath":"/products/kriyojenik-sivilar-custom.jpg","uploadedBy":1,"deletedAt":null,"createdAt":"2025-12-20T13:52:09.000Z","updatedAt":"2025-12-20T16:48:04.000Z"},{"id":20,"filename":"gida-gazlari-custom.jpg","originalName":"gida-gazlari-custom.jpg","mimeType":"image/jpeg","size":82976,"url":"/products/gida-gazlari-custom.jpg","originalPath":"/products/gida-gazlari-custom.jpg","uploadedBy":1,"deletedAt":null,"createdAt":"2025-12-20T13:52:05.000Z","updatedAt":"2025-12-20T16:48:04.000Z"},{"id":17,"filename":"endustriyel-gazlar-custom.jpg","originalName":"endustriyel-gazlar-custom.jpg","mimeType":"image/jpeg","size":223373,"url":"/products/endustriyel-gazlar-custom.jpg","originalPath":"/products/endustriyel-gazlar-custom.jpg","uploadedBy":1,"deletedAt":null,"createdAt":"2025-12-20T13:52:04.000Z","updatedAt":"2025-12-20T16:48:04.000Z"},{"id":11,"filename":"next.svg","originalName":"next.svg","mimeType":"image/svg+xml","size":1375,"url":"/next.svg","originalPath":null,"uploadedBy":1,"deletedAt":null,"createdAt":"2025-12-20T13:52:01.000Z","updatedAt":"2025-12-20T13:52:01.000Z"},{"id":10,"filename":"logo.jpg","originalName":"logo.jpg","mimeType":"image/jpeg","size":1868647,"url":"/logo.jpg","originalPath":null,"uploadedBy":1,"deletedAt":null,"createdAt":"2025-12-20T13:52:00.000Z","updatedAt":"2025-12-20T13:52:00.000Z"},{"id":9,"filename":"logo-clean.png","originalName":"logo-clean.png","mimeType":"image/png","size":44308,"url":"/logo-clean.png","originalPath":null,"uploadedBy":1,"deletedAt":null,"createdAt":"2025-12-20T13:52:00.000Z","updatedAt":"2025-12-20T13:52:00.000Z"},{"id":6,"filename":"industrial-cylinders-2.png","originalName":"industrial-cylinders-2.png","mimeType":"image/png","size":1006861,"url":"/hero/industrial-cylinders-2.png","originalPath":null,"uploadedBy":1,"deletedAt":null,"createdAt":"2025-12-20T13:51:58.000Z","updatedAt":"2025-12-20T13:51:58.000Z"},{"id":5,"filename":"industrial-cylinders-1.png","originalName":"industrial-cylinders-1.png","mimeType":"image/png","size":1026899,"url":"/hero/industrial-cylinders-1.png","originalPath":null,"uploadedBy":1,"deletedAt":null,"createdAt":"2025-12-20T13:51:58.000Z","updatedAt":"2025-12-20T13:51:58.000Z"},{"id":4,"filename":"globe.svg","originalName":"globe.svg","mimeType":"image/svg+xml","size":1035,"url":"/globe.svg","originalPath":null,"uploadedBy":1,"deletedAt":null,"createdAt":"2025-12-20T13:51:57.000Z","updatedAt":"2025-12-20T13:51:57.000Z"},{"id":3,"filename":"file.svg","originalName":"file.svg","mimeType":"image/svg+xml","size":391,"url":"/file.svg","originalPath":null,"uploadedBy":1,"deletedAt":null,"createdAt":"2025-12-20T13:51:57.000Z","updatedAt":"2025-12-20T13:51:57.000Z"},{"id":2,"filename":"dashboard-logo.png","originalName":"dashboard-logo.png","mimeType":"image/png","size":44308,"url":"/dashboard-logo.png","originalPath":null,"uploadedBy":1,"deletedAt":null,"createdAt":"2025-12-20T13:51:56.000Z","updatedAt":"2025-12-20T13:51:56.000Z"},{"id":1,"filename":"dashboard-banner.png","originalName":"dashboard-banner.png","mimeType":"image/png","size":568072,"url":"/dashboard-banner.png","originalPath":null,"uploadedBy":1,"deletedAt":null,"createdAt":"2025-12-20T13:51:55.000Z","updatedAt":"2025-12-20T13:51:55.000Z"}]}